md_inputs.py
md_inputs-1.1.dist-info/METADATA
md_inputs-1.1.dist-info/WHEEL
md_inputs-1.1.dist-info/top_level.txt
md_inputs-1.1.dist-info/RECORD
