Metadata-Version: 2.1
Name: md-inputs
Version: 1.1
Summary: Python-mardown extension for inputs(text, select, checkbox...) in markdown document
Home-page: https://www.python.org/sigs/distutils-sig/
Author: Gavin Guo
Author-email: gghyoo@qq.com
Requires-Dist: markdown (>=3.0)
